{
  "name": "Jessie Patton",
  "age": 46,
  "address": {
    "street": "Toom Center",
    "city": "Bucvogpop",
    "state": "MN",
    "zip": "19367"
  },
  "contact": {
    "phone": "(922) 783-4739",
    "servicePhone": "800736826"
  },
  "birthday": "1975-06-22T10:28:56.077Z",
  "ip": "7.235.159.108",
  "foo": "bar",
  "profile": {
    "about": "Ofnasa lebiz mog re evo bir pev kaheho viaf bakisa luhgawras niwiba. Lecama beuw wuhabarog ve zosav aljom usro asnepa revwac foeba pacfim za neviap ka. Ipeg ne juba genlewev ev okutug rih lipuwog vu pahzesu renakah sageg vama ihcioc kadac vebwo caz. Anarit nowe lecdenwos dakavzo gilag werahad do hapsabil fagosila garim oci rowim ujhehheg. Rudah huvpo li sulcu do oraojo mow teletin gajevzol hesfiwa wugod pemaz nubligal ki fizu ter. Soz logwoki zuf regfuepi kohe livlitgit ezoje pijwa ozo irlenud tu kajdev etgem ejo kiru loig ulebijvom.",
    "bio": "Leka awkis fesfuf lirahjij nelusi ungepo midetuh sewuba mowu gami alguwol gukab pi sac cohgav ictap suwod tepva. Cimour ku to tir huf guc johro berma lagumun kuuj fe wopwok. Uleoc foabuini naopi ceov cukku fe tud sujol wefiful lufebo vofad pe wimojo wupelrim jik. Potigbij maduzwe elu julok ge safgegmu vifsoseg mec tido fimceojo ri mazan evatuhu mohuvik. Tecez dagew sorej dudtu setef woc tufi itu sioja hoite fob usejkip efi bihci. Me guz ruk fep pontaho fe ug ofa vof irbatram miizje ur upasi zadip pe. Po zazo fizki jaazesu se gad nejintov lozuw gunaca ajwuc ketcob ne."
  },
  "apiKey": "af549d28070ea66491bb5d92585f32c550fc013477cf23da3dcc0d9d90b13bd7",
  "currency": {
    "code": "BDT",
    "name": "Bangladesh Taka"
  }
}